{
  "configVersion": 1,
  "timestamp": 1590257418479,
  "index": "/index.html",
  "assetGroups": [
    {
      "name": "app",
      "installMode": "prefetch",
      "updateMode": "prefetch",
      "urls": [
        "/5-es2015.a4fe9ba07de4bf5f7ee9.js",
        "/5-es5.a4fe9ba07de4bf5f7ee9.js",
        "/6-es2015.20983c896ee80e3441f3.js",
        "/6-es5.20983c896ee80e3441f3.js",
        "/favicon.ico",
        "/index.html",
        "/main-es2015.0058dcd0c29d6b3d5942.js",
        "/main-es5.0058dcd0c29d6b3d5942.js",
        "/manifest.webmanifest",
        "/polyfills-es2015.690002c25ea8557bb4b0.js",
        "/polyfills-es5.9e286f6d9247438cbb02.js",
        "/runtime-es2015.b2eceabec4853acdb429.js",
        "/runtime-es5.b2eceabec4853acdb429.js",
        "/styles.2fd7fb35c6b31c014fa6.css"
      ],
      "patterns": [
        "https:\\/\\/fonts\\.googleapis\\.com\\/css\\?family=Roboto"
      ]
    },
    {
      "name": "assets",
      "installMode": "lazy",
      "updateMode": "prefetch",
      "urls": [
        "/assets/icons/icon-128x128.png",
        "/assets/icons/icon-144x144.png",
        "/assets/icons/icon-152x152.png",
        "/assets/icons/icon-192x192.png",
        "/assets/icons/icon-384x384.png",
        "/assets/icons/icon-512x512.png",
        "/assets/icons/icon-72x72.png",
        "/assets/icons/icon-96x96.png"
      ],
      "patterns": []
    }
  ],
  "dataGroups": [
    {
      "name": "firebase-posts",
      "patterns": [
        "https:\\/\\/angular-blog-practice\\.firebaseio\\.com\\/.*"
      ],
      "strategy": "performance",
      "maxSize": 5,
      "maxAge": 0,
      "version": 1
    }
  ],
  "hashTable": {
    "/5-es2015.a4fe9ba07de4bf5f7ee9.js": "0b929762238349163fb84364aaea0f20cf4a4296",
    "/5-es5.a4fe9ba07de4bf5f7ee9.js": "8d7fcd59b5ac84b6e176c8f3473b2dfc3f08fa1a",
    "/6-es2015.20983c896ee80e3441f3.js": "78029d05b6c2103b51769f96af0bf5ce552306e6",
    "/6-es5.20983c896ee80e3441f3.js": "e8c19148010ddc8ac24f2d7806e643699084892b",
    "/assets/icons/icon-128x128.png": "dae3b6ed49bdaf4327b92531d4b5b4a5d30c7532",
    "/assets/icons/icon-144x144.png": "b0bd89982e08f9bd2b642928f5391915b74799a7",
    "/assets/icons/icon-152x152.png": "7479a9477815dfd9668d60f8b3b2fba709b91310",
    "/assets/icons/icon-192x192.png": "1abd80d431a237a853ce38147d8c63752f10933b",
    "/assets/icons/icon-384x384.png": "329749cd6393768d3131ed6304c136b1ca05f2fd",
    "/assets/icons/icon-512x512.png": "559d9c4318b45a1f2b10596bbb4c960fe521dbcc",
    "/assets/icons/icon-72x72.png": "c457e56089a36952cd67156f9996bc4ce54a5ed9",
    "/assets/icons/icon-96x96.png": "3914125a4b445bf111c5627875fc190f560daa41",
    "/favicon.ico": "22f6a4a3bcaafafb0254e0f2fa4ceb89e505e8b2",
    "/index.html": "bff851b63313e679b549f1e6a45cdda7865aa038",
    "/main-es2015.0058dcd0c29d6b3d5942.js": "7d6c28906f44f596363c25e06e53060fd0b45770",
    "/main-es5.0058dcd0c29d6b3d5942.js": "d94d6640bf51d8e0506feefee787d76c1f576dd3",
    "/manifest.webmanifest": "ed42393c5e7857276b50cc49201248d958986c00",
    "/polyfills-es2015.690002c25ea8557bb4b0.js": "72ad4ccc0a3916ae4598199447cdeadd6d380570",
    "/polyfills-es5.9e286f6d9247438cbb02.js": "89222a28dbabb780fc372d33834080e0cd3083d9",
    "/runtime-es2015.b2eceabec4853acdb429.js": "e46310a30910c6314a032188fcb429045b4b1cca",
    "/runtime-es5.b2eceabec4853acdb429.js": "de0a33469254e8559045cfb8d972abdb4ec4bcde",
    "/styles.2fd7fb35c6b31c014fa6.css": "6a9de7e0362377bd0c0b6605baea0066299bdb87"
  },
  "navigationUrls": [
    {
      "positive": true,
      "regex": "^\\/.*$"
    },
    {
      "positive": false,
      "regex": "^\\/(?:.+\\/)?[^/]*\\.[^/]*$"
    },
    {
      "positive": false,
      "regex": "^\\/(?:.+\\/)?[^/]*__[^/]*$"
    },
    {
      "positive": false,
      "regex": "^\\/(?:.+\\/)?[^/]*__[^/]*\\/.*$"
    }
  ]
}